google_auth_lite-0.1.1.dist-info/licenses/LICENSE
google_auth_rewired/__init__.py
google_auth_rewired/cli.py
google_auth_rewired/config.py
google_auth_rewired/impersonation.py
google_auth_rewired/lite.py
google_auth_rewired/oauth_flow.py
google_auth_rewired/scopes.py
google_auth_rewired/utils.py
google_auth_lite-0.1.1.dist-info/METADATA
google_auth_lite-0.1.1.dist-info/WHEEL
google_auth_lite-0.1.1.dist-info/top_level.txt
google_auth_lite-0.1.1.dist-info/RECORD
