Metadata-Version: 2.4
Name: google-auth-lite
Version: 0.1.1
Summary: A lightweight Google Auth SDK for service accounts and OAuth2 login — clean, modern, and dev-focused.
Author-email: Cure Protocols <founder@cureprotocols.com>
License-Expression: MIT
Project-URL: Homepage, https://github.com/cureprotocols/google-auth-rewired
Project-URL: Repository, https://github.com/cureprotocols/google-auth-rewired
Project-URL: Documentation, https://github.com/cureprotocols/google-auth-rewired#readme
Keywords: google-auth,oauth2,service-accounts,api-client,gcp
Requires-Python: >=3.8
License-File: LICENSE
Requires-Dist: requests>=2.31.0
Requires-Dist: requests-oauthlib>=1.3.1
Requires-Dist: google-auth>=2.0.0
Requires-Dist: flask>=2.3.3
Dynamic: license-file
